src/__init__.py
src/benchmark.py
src/config.py
src/exceptions.py
src/main.py
src/pronoun_classifier.py
src/run_phase2.py
src/utils.py
src/verify_phase2.py
src/analyzers/__init__.py
src/analyzers/base.py
src/data/__init__.py
src/data/models.py
src/data/versioning.py
src/extractors/__init__.py
src/extractors/base.py
src/extractors/coreference_extractor.py
src/extractors/phrase_extractor.py
src/extractors/pronoun_extractor.py
src/extractors/relationship_extractor.py
src/multi_file/__init__.py
src/multi_file/advanced_analysis_features.py
src/multi_file/cross_file_coreference_resolver.py
src/multi_file/enhanced_output_system.py
src/multi_file/multi_file_batch_processor.py
src/multi_file/unified_relationship_model.py
src/multi_file/unified_sentence_manager.py
src/parsers/__init__.py
src/parsers/adaptive_tsv_parser.py
src/parsers/base.py
src/parsers/incomplete_format_parser.py
src/parsers/preamble_parser.py
src/parsers/tsv_parser.py
src/utils/__init__.py
src/utils/env_loader.py
src/utils/format_detector.py
src/visualization/__init__.py
src/visualization/interactive_visualizer.py
clausemate-2.0.1.dist-info/METADATA
clausemate-2.0.1.dist-info/WHEEL
clausemate-2.0.1.dist-info/entry_points.txt
clausemate-2.0.1.dist-info/top_level.txt
clausemate-2.0.1.dist-info/RECORD
