Metadata-Version: 2.4
Name: clausemate
Version: 2.0.1
Summary: German pronoun clause mate extraction and analysis tool
Author-email: Job Schepens <job.schepens@uni-koeln.com>
License-Expression: MIT
Project-URL: Homepage, https://github.com/jobschepens/clausemate
Project-URL: Documentation, https://github.com/jobschepens/clausemate#readme
Project-URL: Repository, https://github.com/jobschepens/clausemate.git
Project-URL: Bug Tracker, https://github.com/jobschepens/clausemate/issues
Keywords: linguistics,computational-linguistics,german,pronouns,coreference
Classifier: Development Status :: 4 - Beta
Classifier: Intended Audience :: Science/Research
Classifier: Programming Language :: Python :: 3
Classifier: Programming Language :: Python :: 3.11
Classifier: Topic :: Scientific/Engineering :: Information Analysis
Classifier: Topic :: Text Processing :: Linguistic
Requires-Python: >=3.11
Requires-Dist: pandas<3.0.0,>=1.3.0
Provides-Extra: dev
Requires-Dist: pytest>=7.0.0; extra == "dev"
Requires-Dist: pytest-cov>=4.0.0; extra == "dev"
Requires-Dist: mypy>=1.0.0; extra == "dev"
Requires-Dist: ruff>=0.1.0; extra == "dev"
Requires-Dist: pre-commit>=2.20.0; extra == "dev"
Requires-Dist: bandit>=1.7.0; extra == "dev"
Requires-Dist: safety>=2.0.0; extra == "dev"
Requires-Dist: nox>=2023.4.22; extra == "dev"
Requires-Dist: hypothesis>=6.0.0; extra == "dev"
Provides-Extra: future
Requires-Dist: spacy>=3.4.0; extra == "future"
Requires-Dist: scikit-learn>=1.0.0; extra == "future"
Requires-Dist: plotly>=5.0.0; extra == "future"
Requires-Dist: streamlit>=1.0.0; extra == "future"
Provides-Extra: benchmark
Requires-Dist: memory-profiler>=0.60.0; extra == "benchmark"
Requires-Dist: line-profiler>=4.0.0; extra == "benchmark"
Requires-Dist: pytest-benchmark>=4.0.0; extra == "benchmark"
Requires-Dist: psutil>=5.0.0; extra == "benchmark"
